ScanWatch
