Metadata-Version: 2.1
Name: ScanWatch
Version: 0.2.0
Summary: Local tracker for address on Ethereum, BSC and Polygon chains
Home-page: https://github.com/EtWnn/ScanWatch
Author: EtWnn
Author-email: EtWnn0x@gmail.com
License: MIT
Keywords: eth bsc polygon wallet save tracking history ethereum matic bnb tracker binance smartchain smart chain
Platform: UNKNOWN
Classifier: Intended Audience :: Developers
Classifier: License :: OSI Approved :: MIT License
Classifier: Operating System :: OS Independent
Classifier: Programming Language :: Python :: 3.7
Classifier: Programming Language :: Python
Classifier: Topic :: Software Development :: Libraries :: Python Modules
License-File: LICENSE
